{
  "responseContext": {
    "visitorData": "Cgs5UlRFTGxXRTBTSSilt5K1BjIKCgJVUxIEGgAgNA%3D%3D",
    "maxAgeSeconds": 0
  },
  "playabilityStatus": {
    "status": "ERROR",
    "reason": "This video is unavailable",
    "skip": {
      "playabilityErrorSkipConfig": {
        "skipOnPlayabilityError": false
      }
    }
  },
  "trackingParams": "CAAQu2kiEwju--K_08aHAxUnheQGHecmItk=",
  "adBreakHeartbeatParams": "Q0FBJTNE",
  "cpnInfo": {
    "cpn": "zVbAkhsTxWTvN-qF",
    "cpnSource": "CPN_SOURCE_TYPE_WATCH_SERVER"
  }
}
