{
  "responseContext": {
    "visitorData": "CgtLQUhHYkFRMm5Tayilt5K1BjIKCgJVUxIEGgAgWw%3D%3D",
    "maxAgeSeconds": 0
  },
  "playabilityStatus": {
    "status": "ERROR",
    "reason": "This video is unavailable",
    "skip": {
      "playabilityErrorSkipConfig": {
        "skipOnPlayabilityError": false
      }
    }
  },
  "trackingParams": "CAAQu2kiEwiZ9_G_08aHAxUvguQGHRXILNg=",
  "adBreakHeartbeatParams": "Q0FBJTNE",
  "cpnInfo": {
    "cpn": "VEef8TowSsLzFxFM",
    "cpnSource": "CPN_SOURCE_TYPE_WATCH_SERVER"
  }
}
