{
  "responseContext": {
    "visitorData": "CgtTTUtvY3VlWmJDQSi_t5O1BjIKCgJVUxIEGgAgYw%3D%3D",
    "maxAgeSeconds": 0
  },
  "playabilityStatus": {
    "status": "OK",
    "playableInEmbed": true
  },
  "streamingData": {
    "expiresInSeconds": "21540",
    "formats": [
      {
        "itag": 18,
        "mimeType": "video/mp4; codecs=\"avc1.42001E, mp4a.40.2\"",
        "bitrate": 69574,
        "width": 360,
        "height": 360,
        "lastModified": "1664127154327492",
        "quality": "medium",
        "xtags": "Cg8KB2hlYXVkaW8SBHRydWU",
        "fps": 25,
        "qualityLabel": "360p",
        "projectionType": "RECTANGULAR",
        "audioQuality": "AUDIO_QUALITY_LOW",
        "approxDurationMs": "232501",
        "audioSampleRate": "22050",
        "audioChannels": 2,
        "signatureCipher": "s=vJfqJfQdSswRQIhqJD6vfKNsCA58PzVa8bGdXASGc91vkKLoClX3F4JZtYGAiA-fOqTRjHOi6SocYnz_X88rNa9OP-M3WCahdrPaZlSqw%3D%3D&sp=sig&url=https://rr1---sn-n4v7snee.googlevideo.com/videoplayback%3Fexpire%3D1722101791%26ei%3Dv9ukZvmhB6T7sfIPm8qFsQI%26ip%3D65.52.125.23%26id%3Do-ALixXmVHCn5pn6QRh1yCEpLtUX7REAiVsO3gfp9GXuwH%26itag%3D18%26source%3Dyoutube%26requiressl%3Dyes%26xpc%3DEgVo2aDSNQ%253D%253D%26mh%3DIa%26mm%3D31%252C29%26mn%3Dsn-n4v7snee%252Csn-o097znzd%26ms%3Dau%252Crdu%26mv%3Du%26mvi%3D1%26pl%3D19%26gcr%3Dus%26bui%3DAXc671K8WWSU_oYXMzKwyMDIFvAEswb_HCsqitk7fJYpA6IuQzJ7MhnjWBNBDyW9TTDKIXQ72S6c0nr_%26vprv%3D1%26xtags%3Dheaudio%253Dtrue%26mime%3Dvideo%252Fmp4%26ns%3D7M62ouxIncP_YhZrsvwHpvoQ%26rqh%3D1%26cnr%3D14%26ratebypass%3Dyes%26dur%3D232.501%26lmt%3D1664127154327492%26mt%3D1722079620%26fvip%3D3%26c%3DWEB_MUSIC_ANALYTICS%26txp%3D5538434%26n%3D8wcJv0IJUPRgGbwNJ%26sparams%3Dexpire%252Cei%252Cip%252Cid%252Citag%252Csource%252Crequiressl%252Cxpc%252Cgcr%252Cbui%252Cvprv%252Cxtags%252Cmime%252Cns%252Crqh%252Ccnr%252Cratebypass%252Cdur%252Clmt%26lsparams%3Dmh%252Cmm%252Cmn%252Cms%252Cmv%252Cmvi%252Cpl%26lsig%3DAGtxev0wRQIhAOTccd9JqaAZq-MhBO8SUugux-7-k2lYP5KRntcKxc6vAiB3XL7H-mgF-oLk2Sty-6fIsqkZaEJIO18Syn3cPIpleQ%253D%253D"
      }
    ],
    "adaptiveFormats": [
      {
        "itag": 137,
        "mimeType": "video/mp4; codecs=\"avc1.640020\"",
        "bitrate": 540084,
        "width": 1078,
        "height": 1080,
        "initRange": {
          "start": "0",
          "end": "742"
        },
        "indexRange": {
          "start": "743",
          "end": "1326"
        },
        "lastModified": "1663923303806130",
        "contentLength": "6434344",
        "quality": "hd1080",
        "fps": 25,
        "qualityLabel": "1080p",
        "projectionType": "RECTANGULAR",
        "averageBitrate": 221492,
        "approxDurationMs": "232400",
        "signatureCipher": "s=OJfzJfQdSswRQIgz3SmeFNfL8Az62lxR6Bj1DdeEsCnRPB86rS3es7_36MCIQCB5bOk81N2xuVRNcaC_VUgDqVMPcj8ogHtPJfzrbxfRQ%3D%3D&sp=sig&url=https://rr1---sn-n4v7snee.googlevideo.com/videoplayback%3Fexpire%3D1722101791%26ei%3Dv9ukZvmhB6T7sfIPm8qFsQI%26ip%3D65.52.125.23%26id%3Do-ALixXmVHCn5pn6QRh1yCEpLtUX7REAiVsO3gfp9GXuwH%26itag%3D137%26source%3Dyoutube%26requiressl%3Dyes%26xpc%3DEgVo2aDSNQ%253D%253D%26mh%3DIa%26mm%3D31%252C29%26mn%3Dsn-n4v7snee%252Csn-o097znzd%26ms%3Dau%252Crdu%26mv%3Du%26mvi%3D1%26pl%3D19%26gcr%3Dus%26bui%3DAXc671Kxpa5WGBBdQuMJBvmlZuBhOkT25C9C8NrneOGxbDCUWHU1mc1m83-JhClmktSvBLkIHnhpnlq2%26vprv%3D1%26mime%3Dvideo%252Fmp4%26ns%3Dol1DDW5uV0EhMgy4YshVy4QQ%26rqh%3D1%26gir%3Dyes%26clen%3D6434344%26dur%3D232.400%26lmt%3D1663923303806130%26mt%3D1722079620%26fvip%3D3%26keepalive%3Dyes%26c%3DWEB_MUSIC_ANALYTICS%26txp%3D5532434%26n%3DRUMqecEU25TSafGvM%26sparams%3Dexpire%252Cei%252Cip%252Cid%252Citag%252Csource%252Crequiressl%252Cxpc%252Cgcr%252Cbui%252Cvprv%252Cmime%252Cns%252Crqh%252Cgir%252Cclen%252Cdur%252Clmt%26lsparams%3Dmh%252Cmm%252Cmn%252Cms%252Cmv%252Cmvi%252Cpl%26lsig%3DAGtxev0wRQIhAOTccd9JqaAZq-MhBO8SUugux-7-k2lYP5KRntcKxc6vAiB3XL7H-mgF-oLk2Sty-6fIsqkZaEJIO18Syn3cPIpleQ%253D%253D"
      },
      {
        "itag": 247,
        "mimeType": "video/webm; codecs=\"vp9\"",
        "bitrate": 1042912,
        "width": 720,
        "height": 722,
        "initRange": {
          "start": "0",
          "end": "219"
        },
        "indexRange": {
          "start": "220",
          "end": "992"
        },
        "lastModified": "1663923071140026",
        "contentLength": "9302465",
        "quality": "hd720",
        "fps": 25,
        "qualityLabel": "720p",
        "projectionType": "RECTANGULAR",
        "averageBitrate": 320222,
        "colorInfo": {
          "primaries": "COLOR_PRIMARIES_BT709",
          "transferCharacteristics": "COLOR_TRANSFER_CHARACTERISTICS_BT709",
          "matrixCoefficients": "COLOR_MATRIX_COEFFICIENTS_BT709"
        },
        "approxDurationMs": "232400",
        "signatureCipher": "s=rJfwJfQdSswRQIgw5puMnKlShARPQ5eYarI27aeBRvMCp2F3_Y_IF2dbZcCIQDAW_O29pTYaKdAr1Dgl6Q_xuNTEHuR3SrcJLvF17WHYA%3D%3D&sp=sig&url=https://rr1---sn-n4v7snee.googlevideo.com/videoplayback%3Fexpire%3D1722101791%26ei%3Dv9ukZvmhB6T7sfIPm8qFsQI%26ip%3D65.52.125.23%26id%3Do-ALixXmVHCn5pn6QRh1yCEpLtUX7REAiVsO3gfp9GXuwH%26itag%3D247%26source%3Dyoutube%26requiressl%3Dyes%26xpc%3DEgVo2aDSNQ%253D%253D%26mh%3DIa%26mm%3D31%252C29%26mn%3Dsn-n4v7snee%252Csn-o097znzd%26ms%3Dau%252Crdu%26mv%3Du%26mvi%3D1%26pl%3D19%26gcr%3Dus%26bui%3DAXc671Kxpa5WGBBdQuMJBvmlZuBhOkT25C9C8NrneOGxbDCUWHU1mc1m83-JhClmktSvBLkIHnhpnlq2%26vprv%3D1%26mime%3Dvideo%252Fwebm%26ns%3Dol1DDW5uV0EhMgy4YshVy4QQ%26rqh%3D1%26gir%3Dyes%26clen%3D9302465%26dur%3D232.400%26lmt%3D1663923071140026%26mt%3D1722079620%26fvip%3D3%26keepalive%3Dyes%26c%3DWEB_MUSIC_ANALYTICS%26txp%3D5537434%26n%3DRUMqecEU25TSafGvM%26sparams%3Dexpire%252Cei%252Cip%252Cid%252Citag%252Csource%252Crequiressl%252Cxpc%252Cgcr%252Cbui%252Cvprv%252Cmime%252Cns%252Crqh%252Cgir%252Cclen%252Cdur%252Clmt%26lsparams%3Dmh%252Cmm%252Cmn%252Cms%252Cmv%252Cmvi%252Cpl%26lsig%3DAGtxev0wRQIhAOTccd9JqaAZq-MhBO8SUugux-7-k2lYP5KRntcKxc6vAiB3XL7H-mgF-oLk2Sty-6fIsqkZaEJIO18Syn3cPIpleQ%253D%253D"
      },
      {
        "itag": 136,
        "mimeType": "video/mp4; codecs=\"avc1.4d401f\"",
        "bitrate": 105752,
        "width": 718,
        "height": 720,
        "initRange": {
          "start": "0",
          "end": "740"
        },
        "indexRange": {
          "start": "741",
          "end": "1324"
        },
        "lastModified": "1663921746990280",
        "contentLength": "1356056",
        "quality": "hd720",
        "fps": 25,
        "qualityLabel": "720p",
        "projectionType": "RECTANGULAR",
        "averageBitrate": 46680,
        "approxDurationMs": "232400",
        "signatureCipher": "s=iJfJJfQdSswRgIhJLH5UvjRWhAMMVe4BHPZ7TAWHkknEw4zg1SCpy_qVlk7AiEAvfatwYJzJ2HD3m3c42AhSRAoONtb40MD985YwAkYdWE%3D&sp=sig&url=https://rr1---sn-n4v7snee.googlevideo.com/videoplayback%3Fexpire%3D1722101791%26ei%3Dv9ukZvmhB6T7sfIPm8qFsQI%26ip%3D65.52.125.23%26id%3Do-ALixXmVHCn5pn6QRh1yCEpLtUX7REAiVsO3gfp9GXuwH%26itag%3D136%26source%3Dyoutube%26requiressl%3Dyes%26xpc%3DEgVo2aDSNQ%253D%253D%26mh%3DIa%26mm%3D31%252C29%26mn%3Dsn-n4v7snee%252Csn-o097znzd%26ms%3Dau%252Crdu%26mv%3Du%26mvi%3D1%26pl%3D19%26gcr%3Dus%26bui%3DAXc671Kxpa5WGBBdQuMJBvmlZuBhOkT25C9C8NrneOGxbDCUWHU1mc1m83-JhClmktSvBLkIHnhpnlq2%26vprv%3D1%26mime%3Dvideo%252Fmp4%26ns%3Dol1DDW5uV0EhMgy4YshVy4QQ%26rqh%3D1%26gir%3Dyes%26clen%3D1356056%26dur%3D232.400%26lmt%3D1663921746990280%26mt%3D1722079620%26fvip%3D3%26keepalive%3Dyes%26c%3DWEB_MUSIC_ANALYTICS%26txp%3D5532434%26n%3DRUMqecEU25TSafGvM%26sparams%3Dexpire%252Cei%252Cip%252Cid%252Citag%252Csource%252Crequiressl%252Cxpc%252Cgcr%252Cbui%252Cvprv%252Cmime%252Cns%252Crqh%252Cgir%252Cclen%252Cdur%252Clmt%26lsparams%3Dmh%252Cmm%252Cmn%252Cms%252Cmv%252Cmvi%252Cpl%26lsig%3DAGtxev0wRQIhAOTccd9JqaAZq-MhBO8SUugux-7-k2lYP5KRntcKxc6vAiB3XL7H-mgF-oLk2Sty-6fIsqkZaEJIO18Syn3cPIpleQ%253D%253D"
      },
      {
        "itag": 135,
        "mimeType": "video/mp4; codecs=\"avc1.4d401e\"",
        "bitrate": 69952,
        "width": 480,
        "height": 480,
        "initRange": {
          "start": "0",
          "end": "739"
        },
        "indexRange": {
          "start": "740",
          "end": "1323"
        },
        "lastModified": "1663921730205876",
        "contentLength": "922493",
        "quality": "large",
        "fps": 25,
        "qualityLabel": "480p",
        "projectionType": "RECTANGULAR",
        "averageBitrate": 31755,
        "approxDurationMs": "232400",
        "signatureCipher": "s=3JfGJfQdSswRgIhGN40OHBEB2AIyLeUD7lcmcAe9g_24zDq6hcOSUOkT-8PAiEAk4jnpU0LGpq3xOLBYxkTBWSlWr0ay-ASYriH9447do8%3D&sp=sig&url=https://rr1---sn-n4v7snee.googlevideo.com/videoplayback%3Fexpire%3D1722101791%26ei%3Dv9ukZvmhB6T7sfIPm8qFsQI%26ip%3D65.52.125.23%26id%3Do-ALixXmVHCn5pn6QRh1yCEpLtUX7REAiVsO3gfp9GXuwH%26itag%3D135%26source%3Dyoutube%26requiressl%3Dyes%26xpc%3DEgVo2aDSNQ%253D%253D%26mh%3DIa%26mm%3D31%252C29%26mn%3Dsn-n4v7snee%252Csn-o097znzd%26ms%3Dau%252Crdu%26mv%3Du%26mvi%3D1%26pl%3D19%26gcr%3Dus%26bui%3DAXc671Kxpa5WGBBdQuMJBvmlZuBhOkT25C9C8NrneOGxbDCUWHU1mc1m83-JhClmktSvBLkIHnhpnlq2%26vprv%3D1%26mime%3Dvideo%252Fmp4%26ns%3Dol1DDW5uV0EhMgy4YshVy4QQ%26rqh%3D1%26gir%3Dyes%26clen%3D922493%26dur%3D232.400%26lmt%3D1663921730205876%26mt%3D1722079620%26fvip%3D3%26keepalive%3Dyes%26c%3DWEB_MUSIC_ANALYTICS%26txp%3D5532434%26n%3DRUMqecEU25TSafGvM%26sparams%3Dexpire%252Cei%252Cip%252Cid%252Citag%252Csource%252Crequiressl%252Cxpc%252Cgcr%252Cbui%252Cvprv%252Cmime%252Cns%252Crqh%252Cgir%252Cclen%252Cdur%252Clmt%26lsparams%3Dmh%252Cmm%252Cmn%252Cms%252Cmv%252Cmvi%252Cpl%26lsig%3DAGtxev0wRQIhAOTccd9JqaAZq-MhBO8SUugux-7-k2lYP5KRntcKxc6vAiB3XL7H-mgF-oLk2Sty-6fIsqkZaEJIO18Syn3cPIpleQ%253D%253D"
      },
      {
        "itag": 244,
        "mimeType": "video/webm; codecs=\"vp9\"",
        "bitrate": 438356,
        "width": 480,
        "height": 480,
        "initRange": {
          "start": "0",
          "end": "219"
        },
        "indexRange": {
          "start": "220",
          "end": "992"
        },
        "lastModified": "1663921800196334",
        "contentLength": "5122192",
        "quality": "large",
        "fps": 25,
        "qualityLabel": "480p",
        "projectionType": "RECTANGULAR",
        "averageBitrate": 176323,
        "colorInfo": {
          "primaries": "COLOR_PRIMARIES_BT709",
          "transferCharacteristics": "COLOR_TRANSFER_CHARACTERISTICS_BT709",
          "matrixCoefficients": "COLOR_MATRIX_COEFFICIENTS_BT709"
        },
        "approxDurationMs": "232400",
        "signatureCipher": "s=yJf8JfQdSswRQIg8GKDBENuOuAS2opIFciN5AOj9KmXxgYgjzcIMVYUOP4CIQCDfv_KVp1Rt6Hx3WMNNvvRNLXdnwXZxcjxYt8iaRaxbQ%3D%3D&sp=sig&url=https://rr1---sn-n4v7snee.googlevideo.com/videoplayback%3Fexpire%3D1722101791%26ei%3Dv9ukZvmhB6T7sfIPm8qFsQI%26ip%3D65.52.125.23%26id%3Do-ALixXmVHCn5pn6QRh1yCEpLtUX7REAiVsO3gfp9GXuwH%26itag%3D244%26source%3Dyoutube%26requiressl%3Dyes%26xpc%3DEgVo2aDSNQ%253D%253D%26mh%3DIa%26mm%3D31%252C29%26mn%3Dsn-n4v7snee%252Csn-o097znzd%26ms%3Dau%252Crdu%26mv%3Du%26mvi%3D1%26pl%3D19%26gcr%3Dus%26bui%3DAXc671Kxpa5WGBBdQuMJBvmlZuBhOkT25C9C8NrneOGxbDCUWHU1mc1m83-JhClmktSvBLkIHnhpnlq2%26vprv%3D1%26mime%3Dvideo%252Fwebm%26ns%3Dol1DDW5uV0EhMgy4YshVy4QQ%26rqh%3D1%26gir%3Dyes%26clen%3D5122192%26dur%3D232.400%26lmt%3D1663921800196334%26mt%3D1722079620%26fvip%3D3%26keepalive%3Dyes%26c%3DWEB_MUSIC_ANALYTICS%26txp%3D5537434%26n%3DRUMqecEU25TSafGvM%26sparams%3Dexpire%252Cei%252Cip%252Cid%252Citag%252Csource%252Crequiressl%252Cxpc%252Cgcr%252Cbui%252Cvprv%252Cmime%252Cns%252Crqh%252Cgir%252Cclen%252Cdur%252Clmt%26lsparams%3Dmh%252Cmm%252Cmn%252Cms%252Cmv%252Cmvi%252Cpl%26lsig%3DAGtxev0wRQIhAOTccd9JqaAZq-MhBO8SUugux-7-k2lYP5KRntcKxc6vAiB3XL7H-mgF-oLk2Sty-6fIsqkZaEJIO18Syn3cPIpleQ%253D%253D"
      },
      {
        "itag": 134,
        "mimeType": "video/mp4; codecs=\"avc1.4d4015\"",
        "bitrate": 44568,
        "width": 360,
        "height": 360,
        "initRange": {
          "start": "0",
          "end": "740"
        },
        "indexRange": {
          "start": "741",
          "end": "1324"
        },
        "lastModified": "1663921772011291",
        "contentLength": "615645",
        "quality": "medium",
        "fps": 25,
        "qualityLabel": "360p",
        "projectionType": "RECTANGULAR",
        "averageBitrate": 21192,
        "highReplication": true,
        "approxDurationMs": "232400",
        "signatureCipher": "s=oJfeJfQdSswRQIgetGpVKekfUAoQwPzsDDMlsB0b3cNG8GtjCjk1rwC6qwCIQDn8r2t-sqr4UHVTL-brDt-NI-47sqmjlxGyRfCX3fijw%3D%3D&sp=sig&url=https://rr1---sn-n4v7snee.googlevideo.com/videoplayback%3Fexpire%3D1722101791%26ei%3Dv9ukZvmhB6T7sfIPm8qFsQI%26ip%3D65.52.125.23%26id%3Do-ALixXmVHCn5pn6QRh1yCEpLtUX7REAiVsO3gfp9GXuwH%26itag%3D134%26source%3Dyoutube%26requiressl%3Dyes%26xpc%3DEgVo2aDSNQ%253D%253D%26mh%3DIa%26mm%3D31%252C29%26mn%3Dsn-n4v7snee%252Csn-o097znzd%26ms%3Dau%252Crdu%26mv%3Du%26mvi%3D1%26pl%3D19%26gcr%3Dus%26bui%3DAXc671Kxpa5WGBBdQuMJBvmlZuBhOkT25C9C8NrneOGxbDCUWHU1mc1m83-JhClmktSvBLkIHnhpnlq2%26vprv%3D1%26mime%3Dvideo%252Fmp4%26ns%3Dol1DDW5uV0EhMgy4YshVy4QQ%26rqh%3D1%26gir%3Dyes%26clen%3D615645%26dur%3D232.400%26lmt%3D1663921772011291%26mt%3D1722079620%26fvip%3D3%26keepalive%3Dyes%26c%3DWEB_MUSIC_ANALYTICS%26txp%3D5532434%26n%3DRUMqecEU25TSafGvM%26sparams%3Dexpire%252Cei%252Cip%252Cid%252Citag%252Csource%252Crequiressl%252Cxpc%252Cgcr%252Cbui%252Cvprv%252Cmime%252Cns%252Crqh%252Cgir%252Cclen%252Cdur%252Clmt%26lsparams%3Dmh%252Cmm%252Cmn%252Cms%252Cmv%252Cmvi%252Cpl%26lsig%3DAGtxev0wRQIhAOTccd9JqaAZq-MhBO8SUugux-7-k2lYP5KRntcKxc6vAiB3XL7H-mgF-oLk2Sty-6fIsqkZaEJIO18Syn3cPIpleQ%253D%253D"
      },
      {
        "itag": 243,
        "mimeType": "video/webm; codecs=\"vp9\"",
        "bitrate": 240776,
        "width": 360,
        "height": 360,
        "initRange": {
          "start": "0",
          "end": "219"
        },
        "indexRange": {
          "start": "220",
          "end": "991"
        },
        "lastModified": "1663921771741665",
        "contentLength": "2846870",
        "quality": "medium",
        "fps": 25,
        "qualityLabel": "360p",
        "projectionType": "RECTANGULAR",
        "averageBitrate": 97998,
        "colorInfo": {
          "primaries": "COLOR_PRIMARIES_BT709",
          "transferCharacteristics": "COLOR_TRANSFER_CHARACTERISTICS_BT709",
          "matrixCoefficients": "COLOR_MATRIX_COEFFICIENTS_BT709"
        },
        "approxDurationMs": "232400",
        "signatureCipher": "s=DJfsJfQdSswRQIgsIOeOAplNgA7jhOQkt4nwvPpxLjlQbj01XF2_XK491gCIQDLoV73sXsLCLsUOywb_APAtCPs6FD8IbF9lUdzYm1R_g%3D%3D&sp=sig&url=https://rr1---sn-n4v7snee.googlevideo.com/videoplayback%3Fexpire%3D1722101791%26ei%3Dv9ukZvmhB6T7sfIPm8qFsQI%26ip%3D65.52.125.23%26id%3Do-ALixXmVHCn5pn6QRh1yCEpLtUX7REAiVsO3gfp9GXuwH%26itag%3D243%26source%3Dyoutube%26requiressl%3Dyes%26xpc%3DEgVo2aDSNQ%253D%253D%26mh%3DIa%26mm%3D31%252C29%26mn%3Dsn-n4v7snee%252Csn-o097znzd%26ms%3Dau%252Crdu%26mv%3Du%26mvi%3D1%26pl%3D19%26gcr%3Dus%26bui%3DAXc671Kxpa5WGBBdQuMJBvmlZuBhOkT25C9C8NrneOGxbDCUWHU1mc1m83-JhClmktSvBLkIHnhpnlq2%26vprv%3D1%26mime%3Dvideo%252Fwebm%26ns%3Dol1DDW5uV0EhMgy4YshVy4QQ%26rqh%3D1%26gir%3Dyes%26clen%3D2846870%26dur%3D232.400%26lmt%3D1663921771741665%26mt%3D1722079620%26fvip%3D3%26keepalive%3Dyes%26c%3DWEB_MUSIC_ANALYTICS%26txp%3D5537434%26n%3DRUMqecEU25TSafGvM%26sparams%3Dexpire%252Cei%252Cip%252Cid%252Citag%252Csource%252Crequiressl%252Cxpc%252Cgcr%252Cbui%252Cvprv%252Cmime%252Cns%252Crqh%252Cgir%252Cclen%252Cdur%252Clmt%26lsparams%3Dmh%252Cmm%252Cmn%252Cms%252Cmv%252Cmvi%252Cpl%26lsig%3DAGtxev0wRQIhAOTccd9JqaAZq-MhBO8SUugux-7-k2lYP5KRntcKxc6vAiB3XL7H-mgF-oLk2Sty-6fIsqkZaEJIO18Syn3cPIpleQ%253D%253D"
      },
      {
        "itag": 133,
        "mimeType": "video/mp4; codecs=\"avc1.4d400c\"",
        "bitrate": 24528,
        "width": 240,
        "height": 240,
        "initRange": {
          "start": "0",
          "end": "738"
        },
        "indexRange": {
          "start": "739",
          "end": "1322"
        },
        "lastModified": "1663921771879013",
        "contentLength": "378291",
        "quality": "small",
        "fps": 25,
        "qualityLabel": "240p",
        "projectionType": "RECTANGULAR",
        "averageBitrate": 13022,
        "approxDurationMs": "232400",
        "signatureCipher": "s=0JflJfQdSswRgIhlOh5cP4YyaAQWQRZ0hl4XdAxz5gYmAvvk3SsOYZeCRQxAiEA_uSiuwVF8WT6oG4w5Ot6wpe3ZDsEAX6aXXZvTo4SyVY%3D&sp=sig&url=https://rr1---sn-n4v7snee.googlevideo.com/videoplayback%3Fexpire%3D1722101791%26ei%3Dv9ukZvmhB6T7sfIPm8qFsQI%26ip%3D65.52.125.23%26id%3Do-ALixXmVHCn5pn6QRh1yCEpLtUX7REAiVsO3gfp9GXuwH%26itag%3D133%26source%3Dyoutube%26requiressl%3Dyes%26xpc%3DEgVo2aDSNQ%253D%253D%26mh%3DIa%26mm%3D31%252C29%26mn%3Dsn-n4v7snee%252Csn-o097znzd%26ms%3Dau%252Crdu%26mv%3Du%26mvi%3D1%26pl%3D19%26gcr%3Dus%26bui%3DAXc671Kxpa5WGBBdQuMJBvmlZuBhOkT25C9C8NrneOGxbDCUWHU1mc1m83-JhClmktSvBLkIHnhpnlq2%26vprv%3D1%26mime%3Dvideo%252Fmp4%26ns%3Dol1DDW5uV0EhMgy4YshVy4QQ%26rqh%3D1%26gir%3Dyes%26clen%3D378291%26dur%3D232.400%26lmt%3D1663921771879013%26mt%3D1722079620%26fvip%3D3%26keepalive%3Dyes%26c%3DWEB_MUSIC_ANALYTICS%26txp%3D5532434%26n%3DRUMqecEU25TSafGvM%26sparams%3Dexpire%252Cei%252Cip%252Cid%252Citag%252Csource%252Crequiressl%252Cxpc%252Cgcr%252Cbui%252Cvprv%252Cmime%252Cns%252Crqh%252Cgir%252Cclen%252Cdur%252Clmt%26lsparams%3Dmh%252Cmm%252Cmn%252Cms%252Cmv%252Cmvi%252Cpl%26lsig%3DAGtxev0wRQIhAOTccd9JqaAZq-MhBO8SUugux-7-k2lYP5KRntcKxc6vAiB3XL7H-mgF-oLk2Sty-6fIsqkZaEJIO18Syn3cPIpleQ%253D%253D"
      },
      {
        "itag": 242,
        "mimeType": "video/webm; codecs=\"vp9\"",
        "bitrate": 131184,
        "width": 240,
        "height": 240,
        "initRange": {
          "start": "0",
          "end": "216"
        },
        "indexRange": {
          "start": "217",
          "end": "988"
        },
        "lastModified": "1663921802925557",
        "contentLength": "1583866",
        "quality": "small",
        "fps": 25,
        "qualityLabel": "240p",
        "projectionType": "RECTANGULAR",
        "averageBitrate": 54522,
        "colorInfo": {
          "primaries": "COLOR_PRIMARIES_BT709",
          "transferCharacteristics": "COLOR_TRANSFER_CHARACTERISTICS_BT709",
          "matrixCoefficients": "COLOR_MATRIX_COEFFICIENTS_BT709"
        },
        "approxDurationMs": "232400",
        "signatureCipher": "s=EJfqJfQdSswRQIgqMy5AdtIglAHolSRXEY-DNDXXWFvoBxwa5yExcCP53QCIQDENo8XxyHAJdvDyUsILA_3G60_bVu7U-RIp5BV_IkPug%3D%3D&sp=sig&url=https://rr1---sn-n4v7snee.googlevideo.com/videoplayback%3Fexpire%3D1722101791%26ei%3Dv9ukZvmhB6T7sfIPm8qFsQI%26ip%3D65.52.125.23%26id%3Do-ALixXmVHCn5pn6QRh1yCEpLtUX7REAiVsO3gfp9GXuwH%26itag%3D242%26source%3Dyoutube%26requiressl%3Dyes%26xpc%3DEgVo2aDSNQ%253D%253D%26mh%3DIa%26mm%3D31%252C29%26mn%3Dsn-n4v7snee%252Csn-o097znzd%26ms%3Dau%252Crdu%26mv%3Du%26mvi%3D1%26pl%3D19%26gcr%3Dus%26bui%3DAXc671Kxpa5WGBBdQuMJBvmlZuBhOkT25C9C8NrneOGxbDCUWHU1mc1m83-JhClmktSvBLkIHnhpnlq2%26vprv%3D1%26mime%3Dvideo%252Fwebm%26ns%3Dol1DDW5uV0EhMgy4YshVy4QQ%26rqh%3D1%26gir%3Dyes%26clen%3D1583866%26dur%3D232.400%26lmt%3D1663921802925557%26mt%3D1722079620%26fvip%3D3%26keepalive%3Dyes%26c%3DWEB_MUSIC_ANALYTICS%26txp%3D5537434%26n%3DRUMqecEU25TSafGvM%26sparams%3Dexpire%252Cei%252Cip%252Cid%252Citag%252Csource%252Crequiressl%252Cxpc%252Cgcr%252Cbui%252Cvprv%252Cmime%252Cns%252Crqh%252Cgir%252Cclen%252Cdur%252Clmt%26lsparams%3Dmh%252Cmm%252Cmn%252Cms%252Cmv%252Cmvi%252Cpl%26lsig%3DAGtxev0wRQIhAOTccd9JqaAZq-MhBO8SUugux-7-k2lYP5KRntcKxc6vAiB3XL7H-mgF-oLk2Sty-6fIsqkZaEJIO18Syn3cPIpleQ%253D%253D"
      },
      {
        "itag": 160,
        "mimeType": "video/mp4; codecs=\"avc1.4d400b\"",
        "bitrate": 13944,
        "width": 144,
        "height": 144,
        "initRange": {
          "start": "0",
          "end": "738"
        },
        "indexRange": {
          "start": "739",
          "end": "1322"
        },
        "lastModified": "1663921727607356",
        "contentLength": "252748",
        "quality": "tiny",
        "fps": 25,
        "qualityLabel": "144p",
        "projectionType": "RECTANGULAR",
        "averageBitrate": 8700,
        "approxDurationMs": "232400",
        "signatureCipher": "s=gJfSJfQdSswRQIgSE01XBWHgvArjabFpKlc2actmF9s81mp0I69tMaKNs0CIQDQGynkk6cD2K8mN5EbJf8w7GdfJt-cbhOa9Ks7j0xYyQ%3D%3D&sp=sig&url=https://rr1---sn-n4v7snee.googlevideo.com/videoplayback%3Fexpire%3D1722101791%26ei%3Dv9ukZvmhB6T7sfIPm8qFsQI%26ip%3D65.52.125.23%26id%3Do-ALixXmVHCn5pn6QRh1yCEpLtUX7REAiVsO3gfp9GXuwH%26itag%3D160%26source%3Dyoutube%26requiressl%3Dyes%26xpc%3DEgVo2aDSNQ%253D%253D%26mh%3DIa%26mm%3D31%252C29%26mn%3Dsn-n4v7snee%252Csn-o097znzd%26ms%3Dau%252Crdu%26mv%3Du%26mvi%3D1%26pl%3D19%26gcr%3Dus%26bui%3DAXc671Kxpa5WGBBdQuMJBvmlZuBhOkT25C9C8NrneOGxbDCUWHU1mc1m83-JhClmktSvBLkIHnhpnlq2%26vprv%3D1%26mime%3Dvideo%252Fmp4%26ns%3Dol1DDW5uV0EhMgy4YshVy4QQ%26rqh%3D1%26gir%3Dyes%26clen%3D252748%26dur%3D232.400%26lmt%3D1663921727607356%26mt%3D1722079620%26fvip%3D3%26keepalive%3Dyes%26c%3DWEB_MUSIC_ANALYTICS%26txp%3D5532434%26n%3DRUMqecEU25TSafGvM%26sparams%3Dexpire%252Cei%252Cip%252Cid%252Citag%252Csource%252Crequiressl%252Cxpc%252Cgcr%252Cbui%252Cvprv%252Cmime%252Cns%252Crqh%252Cgir%252Cclen%252Cdur%252Clmt%26lsparams%3Dmh%252Cmm%252Cmn%252Cms%252Cmv%252Cmvi%252Cpl%26lsig%3DAGtxev0wRQIhAOTccd9JqaAZq-MhBO8SUugux-7-k2lYP5KRntcKxc6vAiB3XL7H-mgF-oLk2Sty-6fIsqkZaEJIO18Syn3cPIpleQ%253D%253D"
      },
      {
        "itag": 278,
        "mimeType": "video/webm; codecs=\"vp9\"",
        "bitrate": 59884,
        "width": 144,
        "height": 144,
        "initRange": {
          "start": "0",
          "end": "216"
        },
        "indexRange": {
          "start": "217",
          "end": "986"
        },
        "lastModified": "1663921784936232",
        "contentLength": "765072",
        "quality": "tiny",
        "fps": 25,
        "qualityLabel": "144p",
        "projectionType": "RECTANGULAR",
        "averageBitrate": 26336,
        "colorInfo": {
          "primaries": "COLOR_PRIMARIES_BT709",
          "transferCharacteristics": "COLOR_TRANSFER_CHARACTERISTICS_BT709",
          "matrixCoefficients": "COLOR_MATRIX_COEFFICIENTS_BT709"
        },
        "approxDurationMs": "232400",
        "signatureCipher": "s=oJfdJfQdSswRgIhdNw3a0eIbfA1qulO0OU6q1A1u5AalKmx9bkB0uCSgApoAiEAxgOfZvdjCMsi437gPWL6qMZ6EBgYu8DF89eAaFu2x6c%3D&sp=sig&url=https://rr1---sn-n4v7snee.googlevideo.com/videoplayback%3Fexpire%3D1722101791%26ei%3Dv9ukZvmhB6T7sfIPm8qFsQI%26ip%3D65.52.125.23%26id%3Do-ALixXmVHCn5pn6QRh1yCEpLtUX7REAiVsO3gfp9GXuwH%26itag%3D278%26source%3Dyoutube%26requiressl%3Dyes%26xpc%3DEgVo2aDSNQ%253D%253D%26mh%3DIa%26mm%3D31%252C29%26mn%3Dsn-n4v7snee%252Csn-o097znzd%26ms%3Dau%252Crdu%26mv%3Du%26mvi%3D1%26pl%3D19%26gcr%3Dus%26bui%3DAXc671Kxpa5WGBBdQuMJBvmlZuBhOkT25C9C8NrneOGxbDCUWHU1mc1m83-JhClmktSvBLkIHnhpnlq2%26vprv%3D1%26mime%3Dvideo%252Fwebm%26ns%3Dol1DDW5uV0EhMgy4YshVy4QQ%26rqh%3D1%26gir%3Dyes%26clen%3D765072%26dur%3D232.400%26lmt%3D1663921784936232%26mt%3D1722079620%26fvip%3D3%26keepalive%3Dyes%26c%3DWEB_MUSIC_ANALYTICS%26txp%3D5537434%26n%3DRUMqecEU25TSafGvM%26sparams%3Dexpire%252Cei%252Cip%252Cid%252Citag%252Csource%252Crequiressl%252Cxpc%252Cgcr%252Cbui%252Cvprv%252Cmime%252Cns%252Crqh%252Cgir%252Cclen%252Cdur%252Clmt%26lsparams%3Dmh%252Cmm%252Cmn%252Cms%252Cmv%252Cmvi%252Cpl%26lsig%3DAGtxev0wRQIhAOTccd9JqaAZq-MhBO8SUugux-7-k2lYP5KRntcKxc6vAiB3XL7H-mgF-oLk2Sty-6fIsqkZaEJIO18Syn3cPIpleQ%253D%253D"
      },
      {
        "itag": 140,
        "mimeType": "audio/mp4; codecs=\"mp4a.40.2\"",
        "bitrate": 131176,
        "initRange": {
          "start": "0",
          "end": "667"
        },
        "indexRange": {
          "start": "668",
          "end": "987"
        },
        "lastModified": "1663921057825429",
        "contentLength": "3763877",
        "quality": "tiny",
        "projectionType": "RECTANGULAR",
        "averageBitrate": 129550,
        "highReplication": true,
        "audioQuality": "AUDIO_QUALITY_MEDIUM",
        "approxDurationMs": "232426",
        "audioSampleRate": "44100",
        "audioChannels": 2,
        "signatureCipher": "s=_JfbJfQdSswRQIgbE5JlVfE50A4025gFamobnYe287r9eTg1rhs72m3s9ECIQDjTdXys550dni1LrCGFpMG22mnDuV9Yvuev1jJcdYlNQ%3D%3D&sp=sig&url=https://rr1---sn-n4v7snee.googlevideo.com/videoplayback%3Fexpire%3D1722101791%26ei%3Dv9ukZvmhB6T7sfIPm8qFsQI%26ip%3D65.52.125.23%26id%3Do-ALixXmVHCn5pn6QRh1yCEpLtUX7REAiVsO3gfp9GXuwH%26itag%3D140%26source%3Dyoutube%26requiressl%3Dyes%26xpc%3DEgVo2aDSNQ%253D%253D%26mh%3DIa%26mm%3D31%252C29%26mn%3Dsn-n4v7snee%252Csn-o097znzd%26ms%3Dau%252Crdu%26mv%3Du%26mvi%3D1%26pl%3D19%26gcr%3Dus%26bui%3DAXc671Kxpa5WGBBdQuMJBvmlZuBhOkT25C9C8NrneOGxbDCUWHU1mc1m83-JhClmktSvBLkIHnhpnlq2%26vprv%3D1%26mime%3Daudio%252Fmp4%26ns%3Dol1DDW5uV0EhMgy4YshVy4QQ%26rqh%3D1%26gir%3Dyes%26clen%3D3763877%26dur%3D232.426%26lmt%3D1663921057825429%26mt%3D1722079620%26fvip%3D3%26keepalive%3Dyes%26c%3DWEB_MUSIC_ANALYTICS%26txp%3D5532434%26n%3DRUMqecEU25TSafGvM%26sparams%3Dexpire%252Cei%252Cip%252Cid%252Citag%252Csource%252Crequiressl%252Cxpc%252Cgcr%252Cbui%252Cvprv%252Cmime%252Cns%252Crqh%252Cgir%252Cclen%252Cdur%252Clmt%26lsparams%3Dmh%252Cmm%252Cmn%252Cms%252Cmv%252Cmvi%252Cpl%26lsig%3DAGtxev0wRQIhAOTccd9JqaAZq-MhBO8SUugux-7-k2lYP5KRntcKxc6vAiB3XL7H-mgF-oLk2Sty-6fIsqkZaEJIO18Syn3cPIpleQ%253D%253D"
      },
      {
        "itag": 249,
        "mimeType": "audio/webm; codecs=\"opus\"",
        "bitrate": 57132,
        "initRange": {
          "start": "0",
          "end": "258"
        },
        "indexRange": {
          "start": "259",
          "end": "663"
        },
        "lastModified": "1714387707113106",
        "contentLength": "1547018",
        "quality": "tiny",
        "projectionType": "RECTANGULAR",
        "averageBitrate": 53244,
        "audioQuality": "AUDIO_QUALITY_LOW",
        "approxDurationMs": "232441",
        "audioSampleRate": "48000",
        "audioChannels": 2,
        "signatureCipher": "s=zJf7JfQdSswRAIg7hjr47NgdlA86uzk1ICIQZQ8m5kJmNhP9oFnWWD3hlMCIHIHwJVN3XOVjV5e-7GdRjuSg5f_ORbZUPMci20BDnuj&sp=sig&url=https://rr1---sn-n4v7snee.googlevideo.com/videoplayback%3Fexpire%3D1722101791%26ei%3Dv9ukZvmhB6T7sfIPm8qFsQI%26ip%3D65.52.125.23%26id%3Do-ALixXmVHCn5pn6QRh1yCEpLtUX7REAiVsO3gfp9GXuwH%26itag%3D249%26source%3Dyoutube%26requiressl%3Dyes%26xpc%3DEgVo2aDSNQ%253D%253D%26mh%3DIa%26mm%3D31%252C29%26mn%3Dsn-n4v7snee%252Csn-o097znzd%26ms%3Dau%252Crdu%26mv%3Du%26mvi%3D1%26pl%3D19%26gcr%3Dus%26bui%3DAXc671Kxpa5WGBBdQuMJBvmlZuBhOkT25C9C8NrneOGxbDCUWHU1mc1m83-JhClmktSvBLkIHnhpnlq2%26vprv%3D1%26mime%3Daudio%252Fwebm%26ns%3Dol1DDW5uV0EhMgy4YshVy4QQ%26rqh%3D1%26gir%3Dyes%26clen%3D1547018%26dur%3D232.441%26lmt%3D1714387707113106%26mt%3D1722079620%26fvip%3D3%26keepalive%3Dyes%26c%3DWEB_MUSIC_ANALYTICS%26txp%3D5532434%26n%3DRUMqecEU25TSafGvM%26sparams%3Dexpire%252Cei%252Cip%252Cid%252Citag%252Csource%252Crequiressl%252Cxpc%252Cgcr%252Cbui%252Cvprv%252Cmime%252Cns%252Crqh%252Cgir%252Cclen%252Cdur%252Clmt%26lsparams%3Dmh%252Cmm%252Cmn%252Cms%252Cmv%252Cmvi%252Cpl%26lsig%3DAGtxev0wRQIhAOTccd9JqaAZq-MhBO8SUugux-7-k2lYP5KRntcKxc6vAiB3XL7H-mgF-oLk2Sty-6fIsqkZaEJIO18Syn3cPIpleQ%253D%253D"
      },
      {
        "itag": 250,
        "mimeType": "audio/webm; codecs=\"opus\"",
        "bitrate": 75231,
        "initRange": {
          "start": "0",
          "end": "258"
        },
        "indexRange": {
          "start": "259",
          "end": "663"
        },
        "lastModified": "1714387740686104",
        "contentLength": "2049824",
        "quality": "tiny",
        "projectionType": "RECTANGULAR",
        "averageBitrate": 70549,
        "audioQuality": "AUDIO_QUALITY_LOW",
        "approxDurationMs": "232441",
        "audioSampleRate": "48000",
        "audioChannels": 2,
        "signatureCipher": "s=VJfMJfQdSswRQIhMME0xQjvplAf3WNXQFaqLvAGLckih3dZm1UUBQiSWI95AiBA6r7gl6Xb9hZfMEBzlHNAOT-aI-IyL2zgVwMI6OQ7Qw%3D%3D&sp=sig&url=https://rr1---sn-n4v7snee.googlevideo.com/videoplayback%3Fexpire%3D1722101791%26ei%3Dv9ukZvmhB6T7sfIPm8qFsQI%26ip%3D65.52.125.23%26id%3Do-ALixXmVHCn5pn6QRh1yCEpLtUX7REAiVsO3gfp9GXuwH%26itag%3D250%26source%3Dyoutube%26requiressl%3Dyes%26xpc%3DEgVo2aDSNQ%253D%253D%26mh%3DIa%26mm%3D31%252C29%26mn%3Dsn-n4v7snee%252Csn-o097znzd%26ms%3Dau%252Crdu%26mv%3Du%26mvi%3D1%26pl%3D19%26gcr%3Dus%26bui%3DAXc671Kxpa5WGBBdQuMJBvmlZuBhOkT25C9C8NrneOGxbDCUWHU1mc1m83-JhClmktSvBLkIHnhpnlq2%26vprv%3D1%26mime%3Daudio%252Fwebm%26ns%3Dol1DDW5uV0EhMgy4YshVy4QQ%26rqh%3D1%26gir%3Dyes%26clen%3D2049824%26dur%3D232.441%26lmt%3D1714387740686104%26mt%3D1722079620%26fvip%3D3%26keepalive%3Dyes%26c%3DWEB_MUSIC_ANALYTICS%26txp%3D5532434%26n%3DRUMqecEU25TSafGvM%26sparams%3Dexpire%252Cei%252Cip%252Cid%252Citag%252Csource%252Crequiressl%252Cxpc%252Cgcr%252Cbui%252Cvprv%252Cmime%252Cns%252Crqh%252Cgir%252Cclen%252Cdur%252Clmt%26lsparams%3Dmh%252Cmm%252Cmn%252Cms%252Cmv%252Cmvi%252Cpl%26lsig%3DAGtxev0wRQIhAOTccd9JqaAZq-MhBO8SUugux-7-k2lYP5KRntcKxc6vAiB3XL7H-mgF-oLk2Sty-6fIsqkZaEJIO18Syn3cPIpleQ%253D%253D"
      },
      {
        "itag": 251,
        "mimeType": "audio/webm; codecs=\"opus\"",
        "bitrate": 147283,
        "initRange": {
          "start": "0",
          "end": "258"
        },
        "indexRange": {
          "start": "259",
          "end": "663"
        },
        "lastModified": "1714387707585887",
        "contentLength": "4053791",
        "quality": "tiny",
        "projectionType": "RECTANGULAR",
        "averageBitrate": 139520,
        "audioQuality": "AUDIO_QUALITY_MEDIUM",
        "approxDurationMs": "232441",
        "audioSampleRate": "48000",
        "audioChannels": 2,
        "signatureCipher": "s=eJfhJfQdSswRgIhhIR2x5AHaZAGCOQlg0pvS1AdqkZs5vzc-dBpdnl54meXAiEA9ClFzZiDdrIXifqz1YaLLgZ8ykD5RuEheDKbkDvi5S8%3D&sp=sig&url=https://rr1---sn-n4v7snee.googlevideo.com/videoplayback%3Fexpire%3D1722101791%26ei%3Dv9ukZvmhB6T7sfIPm8qFsQI%26ip%3D65.52.125.23%26id%3Do-ALixXmVHCn5pn6QRh1yCEpLtUX7REAiVsO3gfp9GXuwH%26itag%3D251%26source%3Dyoutube%26requiressl%3Dyes%26xpc%3DEgVo2aDSNQ%253D%253D%26mh%3DIa%26mm%3D31%252C29%26mn%3Dsn-n4v7snee%252Csn-o097znzd%26ms%3Dau%252Crdu%26mv%3Du%26mvi%3D1%26pl%3D19%26gcr%3Dus%26bui%3DAXc671Kxpa5WGBBdQuMJBvmlZuBhOkT25C9C8NrneOGxbDCUWHU1mc1m83-JhClmktSvBLkIHnhpnlq2%26vprv%3D1%26mime%3Daudio%252Fwebm%26ns%3Dol1DDW5uV0EhMgy4YshVy4QQ%26rqh%3D1%26gir%3Dyes%26clen%3D4053791%26dur%3D232.441%26lmt%3D1714387707585887%26mt%3D1722079620%26fvip%3D3%26keepalive%3Dyes%26c%3DWEB_MUSIC_ANALYTICS%26txp%3D5532434%26n%3DRUMqecEU25TSafGvM%26sparams%3Dexpire%252Cei%252Cip%252Cid%252Citag%252Csource%252Crequiressl%252Cxpc%252Cgcr%252Cbui%252Cvprv%252Cmime%252Cns%252Crqh%252Cgir%252Cclen%252Cdur%252Clmt%26lsparams%3Dmh%252Cmm%252Cmn%252Cms%252Cmv%252Cmvi%252Cpl%26lsig%3DAGtxev0wRQIhAOTccd9JqaAZq-MhBO8SUugux-7-k2lYP5KRntcKxc6vAiB3XL7H-mgF-oLk2Sty-6fIsqkZaEJIO18Syn3cPIpleQ%253D%253D"
      }
    ]
  },
  "playbackTracking": {
    "videostatsPlaybackUrl": {
      "baseUrl": "https://s.youtube.com/api/stats/playback?cl=655300395&docid=3YW3W5RPV-0&ei=v9ukZvmhB6T7sfIPm8qFsQI&fexp=&ns=yt&plid=AAYeOQoR1bd4dDuv&el=detailpage&len=233&of=lXXs7UQJzdfMBqrVh7hayA&vm=CAMQARgBOjJBSHFpSlRMc3RNQ01fcm1zVFdLaVFCOW0yaU5aOVVabldRMkdLMi1uVDJpeEk0VFB5QWJeQU9BckJGdG4tSXhPTWdNVVVQbWdYeEtJQTBNakx0cU5NOEcwV2xiT2UwMldBWlFCQVF4YnNhNkhpRFpRYW9lZXNXc21nMlhBTEp6d0JlZy1LV3lkYURKdlJrenhFUbgBAQ"
    },
    "videostatsDelayplayUrl": {
      "baseUrl": "https://s.youtube.com/api/stats/delayplay?cl=655300395&docid=3YW3W5RPV-0&ei=v9ukZvmhB6T7sfIPm8qFsQI&fexp=&ns=yt&plid=AAYeOQoR1bd4dDuv&el=detailpage&len=233&of=lXXs7UQJzdfMBqrVh7hayA&vm=CAMQARgBOjJBSHFpSlRMc3RNQ01fcm1zVFdLaVFCOW0yaU5aOVVabldRMkdLMi1uVDJpeEk0VFB5QWJeQU9BckJGdG4tSXhPTWdNVVVQbWdYeEtJQTBNakx0cU5NOEcwV2xiT2UwMldBWlFCQVF4YnNhNkhpRFpRYW9lZXNXc21nMlhBTEp6d0JlZy1LV3lkYURKdlJrenhFUbgBAQ"
    },
    "videostatsWatchtimeUrl": {
      "baseUrl": "https://s.youtube.com/api/stats/watchtime?cl=655300395&docid=3YW3W5RPV-0&ei=v9ukZvmhB6T7sfIPm8qFsQI&fexp=&ns=yt&plid=AAYeOQoR1bd4dDuv&el=detailpage&len=233&of=lXXs7UQJzdfMBqrVh7hayA&vm=CAMQARgBOjJBSHFpSlRMc3RNQ01fcm1zVFdLaVFCOW0yaU5aOVVabldRMkdLMi1uVDJpeEk0VFB5QWJeQU9BckJGdG4tSXhPTWdNVVVQbWdYeEtJQTBNakx0cU5NOEcwV2xiT2UwMldBWlFCQVF4YnNhNkhpRFpRYW9lZXNXc21nMlhBTEp6d0JlZy1LV3lkYURKdlJrenhFUbgBAQ"
    },
    "ptrackingUrl": {
      "baseUrl": "https://www.youtube.com/ptracking?ei=v9ukZvmhB6T7sfIPm8qFsQI&oid=ghgcd_xPPR_URSW5U_cwtQ&plid=AAYeOQoR1bd4dDuv&pltype=content&ptchn=4taJzeu74geUcYdnENV1Ig&ptk=youtube_single&video_id=3YW3W5RPV-0"
    },
    "qoeUrl": {
      "baseUrl": "https://s.youtube.com/api/stats/qoe?cl=655300395&docid=3YW3W5RPV-0&ei=v9ukZvmhB6T7sfIPm8qFsQI&event=streamingstats&fexp=&ns=yt&plid=AAYeOQoR1bd4dDuv"
    }
  },
  "videoDetails": {
    "videoId": "3YW3W5RPV-0",
    "title": "Carrying Your Love With Me",
    "lengthSeconds": "232",
    "keywords": [
      "George Strait",
      "ジヨージストレイト",
      "ジョージ・ストレイト",
      "Carrying Your Love With Me"
    ],
    "channelId": "UC4taJzeu74geUcYdnENV1Ig",
    "isOwnerViewing": false,
    "shortDescription": "Provided to YouTube by Universal Music Group\n\nCarrying Your Love With Me · George Strait\n\nCarrying Your Love With Me\n\n℗ 1997 MCA Nashville, a Division of UMG Recordings, Inc.\n\nReleased on: 1997-01-01\n\nProducer: Tony Brown\nProducer: George Strait\nStudio  Personnel, Recording  Engineer: Steve Marcantonio\nStudio  Personnel, Mixer: Chuck Ainlay\nComposer  Lyricist: Steve Bogard\nComposer  Lyricist: Jeff Stevens\n\nAuto-generated by YouTube.",
    "isCrawlable": true,
    "thumbnail": {
      "thumbnails": [
        {
          "url": "https://i.ytimg.com/vi/3YW3W5RPV-0/default.jpg",
          "width": 120,
          "height": 90
        },
        {
          "url": "https://i.ytimg.com/vi/3YW3W5RPV-0/mqdefault.jpg",
          "width": 320,
          "height": 180
        },
        {
          "url": "https://i.ytimg.com/vi/3YW3W5RPV-0/hqdefault.jpg",
          "width": 480,
          "height": 360
        },
        {
          "url": "https://i.ytimg.com/vi/3YW3W5RPV-0/sddefault.jpg",
          "width": 640,
          "height": 480
        },
        {
          "url": "https://i.ytimg.com/vi/3YW3W5RPV-0/maxresdefault.jpg",
          "width": 1920,
          "height": 1080
        }
      ]
    },
    "allowRatings": true,
    "viewCount": "33132086",
    "author": "George Strait - Topic",
    "isPrivate": false,
    "isUnpluggedCorpus": false,
    "isLiveContent": false
  },
  "playerConfig": {},
  "trackingParams": "CAAQu2kiEwi5_cPQkMeHAxWkfUwIHRtlISY=",
  "adBreakHeartbeatParams": "Q0FBJTNE"
}
