{
  "responseContext": {
    "visitorData": "CgtJR3RzY0JkNUY3USj8tJK1BjIKCgJVUxIEGgAgLw%3D%3D",
    "serviceTrackingParams": [
      {
        "service": "GFEEDBACK",
        "params": [
          {
            "key": "ipcc",
            "value": "0"
          },
          {
            "key": "is_alc_surface",
            "value": "false"
          },
          {
            "key": "is_viewed_live",
            "value": "False"
          },
          {
            "key": "logged_in",
            "value": "0"
          },
          {
            "key": "e",
            "value": "23946420,23966208,23998056,24004644,24077241,24181174,24241378,24290971,24428948,24456089,24468724,24542367,24548629,39326848,39326916,51009781,51016856,51017346,51020570,51025415,51028056,51041512,51050361,51053689,51060353,51064835,51111738,51114643,51115184,51116067,51117319,51124104,51139379,51144925,51148688,51149607,51152050,51157411,51157841,51158514,51160545,51162170,51165467,51165568,51169117,51176511,51176608,51178982,51182274,51183909,51184022,51189826,51190652,51195231,51200569,51202231,51213807,51217236,51217274,51217504,51219800,51220492,51221011,51221405,51222766,51223961,51224747,51227881,51227903,51228350,51228352,51230478,51230492,51231813,51231864,51232710,51237842,51238486,51238569,51238737,51241028,51241600,51242448,51242767,51243941,51246265,51246798,51247070,51248255,51249840,51251435,51251509,51251675"
          }
        ]
      },
      {
        "service": "ECATCHER",
        "params": [
          {
            "key": "client.version",
            "value": "5.23"
          },
          {
            "key": "client.name",
            "value": "IOS_UNPLUGGED"
          }
        ]
      },
      {
        "service": "BREAKPAD",
        "params": [
          {
            "key": "e",
            "value": "51176511,24286257,51074286,51117319,51176608,51237842,51200569,51246265,51060353,51238737,51245837,51238486,51251675,51210639,24527813,51221405,51158514,24456089,51223961,51242448,51227881,51230478,51064835,51202132,24290971,51160545,51217504,51246798"
          },
          {
            "key": "e2",
            "value": "51149607,51169117,51251509,51162170,51230492,24542367,51009781,51248255,51111738,24548629,51025415,24428948,39326916,51224747,51190652,24220751,51184022,51114643,51221011,51241600,51050361,51016856,51116067,51213807,51139379,51195231,51178982,51231864"
          },
          {
            "key": "e3",
            "value": "51053689,51124104,51189826,51020570,24181174,51251435,51157411,51152050,51219800,24274141,51028056,39326848,51148688"
          }
        ]
      }
    ],
    "maxAgeSeconds": 0
  },
  "playabilityStatus": {
    "status": "UNPLAYABLE",
    "reason": "This video is not available",
    "errorScreen": {
      "playerErrorMessageRenderer": {
        "reason": {
          "runs": [
            {
              "text": "This video is not available"
            }
          ]
        },
        "thumbnail": {
          "thumbnails": [
            {
              "url": "//s.ytimg.com/yts/img/meh7-vflGevej7.png",
              "width": 140,
              "height": 100
            }
          ]
        }
      }
    }
  },
  "videoDetails": {
    "videoId": "3YW3W5RPV-0",
    "title": "Carrying Your Love With Me",
    "lengthSeconds": "232",
    "keywords": [
      "George Strait",
      "ジヨージストレイト",
      "ジョージ・ストレイト",
      "Carrying Your Love With Me"
    ],
    "channelId": "UC4taJzeu74geUcYdnENV1Ig",
    "isOwnerViewing": false,
    "shortDescription": "Provided to YouTube by Universal Music Group\n\nCarrying Your Love With Me · George Strait\n\nCarrying Your Love With Me\n\n℗ 1997 MCA Nashville, a Division of UMG Recordings, Inc.\n\nReleased on: 1997-01-01\n\nProducer: Tony Brown\nProducer: George Strait\nStudio  Personnel, Recording  Engineer: Steve Marcantonio\nStudio  Personnel, Mixer: Chuck Ainlay\nComposer  Lyricist: Steve Bogard\nComposer  Lyricist: Jeff Stevens\n\nAuto-generated by YouTube.",
    "isCrawlable": true,
    "thumbnail": {
      "thumbnails": [
        {
          "url": "https://i.ytimg.com/vi/3YW3W5RPV-0/mqdefault.jpg",
          "width": 320,
          "height": 180
        },
        {
          "url": "https://i.ytimg.com/vi/3YW3W5RPV-0/hqdefault.jpg",
          "width": 480,
          "height": 360
        },
        {
          "url": "https://i.ytimg.com/vi/3YW3W5RPV-0/sddefault.jpg",
          "width": 640,
          "height": 480
        }
      ]
    },
    "allowRatings": true,
    "viewCount": "33129758",
    "author": "George Strait - Topic",
    "isPrivate": false,
    "isUnpluggedCorpus": false,
    "isLiveContent": false
  },
  "trackingParams": "CAAQu2kiEwixrqKy0saHAxWOmuUHHXEOBMk=",
  "adBreakHeartbeatParams": "Q0FBJTNE"
}
